chemica/__init__.py
chemica/chemica.py
chemica-1.1.0.dist-info/LICENSE
chemica-1.1.0.dist-info/METADATA
chemica-1.1.0.dist-info/WHEEL
chemica-1.1.0.dist-info/top_level.txt
chemica-1.1.0.dist-info/RECORD
