Metadata-Version: 2.1
Name: chemica
Version: 1.1.0
Summary: A simple library that takes chemistry to the next level.
Home-page: https://github.com/mishailovic/chemica/
Author: Mikhail Kuznetsov
Author-email: yaunm@yandex.com
License: MIT
Project-URL: Documentation, https://github.com/mishailovic/chemica/blob/main/README.md
Project-URL: Issues, https://github.com/mishailovic/chemica/issues
Keywords: Chemistry,chemical equations
Platform: UNKNOWN
Classifier: License :: OSI Approved :: MIT License
Classifier: Programming Language :: Python
Classifier: Programming Language :: Python :: 3
Classifier: Programming Language :: Python :: 3.7
Classifier: Programming Language :: Python :: 3.8
Classifier: Programming Language :: Python :: 3.9
Classifier: Intended Audience :: Developers
Classifier: Operating System :: OS Independent
Classifier: Programming Language :: Python :: Implementation :: CPython
Classifier: Programming Language :: Python :: Implementation :: PyPy
Classifier: Topic :: Scientific/Engineering :: Chemistry
Classifier: Typing :: Typed
Requires-Python: >=3.7.0
Requires-Dist: urllib3
Requires-Dist: beautifulsoup4
